{
  "headers": {
    "x-amz-version-id": "5X.V54w9QHcxZkeWO2MKiVENj1zm41YM",
    "cross-origin-resource-policy": "same-origin",
    "via": "http/2 edgeproxy-h",
    "date": "Wed, 16 Aug 2023 07:42:45 GMT",
    "last-modified": "Wed, 27 Jul 2022 18:38:31 GMT",
    "server-timing": "fetchSource;dur=94",
    "x-content-type-options": "nosniff",
    "x-amz-cf-id": "PErG3SO1P1DgoXdoHkN9VA4lDeATz8-paDBpkcuUhDm2XfUJmtpowQ==",
    "age": "1331",
    "content-type": "application/typescript; charset=utf-8",
    "content-security-policy": "default-src 'none'; style-src 'unsafe-inline'; sandbox",
    "server": "deno/gcp-europe-central2",
    "referrer-policy": "strict-origin-when-cross-origin",
    "x-amz-cf-pop": "WAW51-P1",
    "accept-ranges": "bytes",
    "vary": "Accept-Encoding, Origin",
    "access-control-allow-origin": "*",
    "cache-control": "public, max-age=31536000, immutable",
    "cross-origin-opener-policy": "same-origin",
    "etag": "\"e4fe68353037ad0798cde8364dabcf86\"",
    "x-cache": "Hit from cloudfront",
    "x-frame-options": "DENY",
    "content-length": "100037",
    "cross-origin-embedder-policy": "same-origin",
    "strict-transport-security": "max-age=63072000; includeSubDomains; preload",
    "x-amz-replication-status": "COMPLETED"
  },
  "url": "https://deno.land/x/web3@v0.11.1/types/buffer.d.ts",
  "now": {
    "secs_since_epoch": 1692173095,
    "nanos_since_epoch": 945322000
  }
}